msal_interactive_token_acquirer/__init__.py
msal_interactive_token_acquirer/msal_interactive_token_acquirer.py
msal_interactive_token_acquirer/requests.py
msal_interactive_token_acquirer/requests_auth.py
msal_interactive_token_acquirer/tools/Microsoft.Bcl.AsyncInterfaces.dll
msal_interactive_token_acquirer/tools/Microsoft.Identity.Client.Desktop.dll
msal_interactive_token_acquirer/tools/Microsoft.Identity.Client.dll
msal_interactive_token_acquirer/tools/Microsoft.Web.WebView2.Core.dll
msal_interactive_token_acquirer/tools/Microsoft.Web.WebView2.WinForms.dll
msal_interactive_token_acquirer/tools/Microsoft.Web.WebView2.Wpf.dll
msal_interactive_token_acquirer/tools/System.Buffers.dll
msal_interactive_token_acquirer/tools/System.Memory.dll
msal_interactive_token_acquirer/tools/System.Numerics.Vectors.dll
msal_interactive_token_acquirer/tools/System.Runtime.CompilerServices.Unsafe.dll
msal_interactive_token_acquirer/tools/System.Text.Encodings.Web.dll
msal_interactive_token_acquirer/tools/System.Text.Json.dll
msal_interactive_token_acquirer/tools/System.Threading.Tasks.Extensions.dll
msal_interactive_token_acquirer/tools/System.ValueTuple.dll
msal_interactive_token_acquirer/tools/WebView2Loader.dll
msal_interactive_token_acquirer/tools/msal_interactive_cli.exe
msal_interactive_token_acquirer/tools/msal_interactive_cli.exe.config
msal_interactive_token_acquirer-1.4.0.dist-info/METADATA
msal_interactive_token_acquirer-1.4.0.dist-info/WHEEL
msal_interactive_token_acquirer-1.4.0.dist-info/top_level.txt
msal_interactive_token_acquirer-1.4.0.dist-info/RECORD
