Metadata-Version: 2.1
Name: msal-interactive-token-acquirer
Version: 1.4.0
Summary: A library to get MSAL token interactively for native client.
Home-page: https://github.com/masamitsu-murase/msal_interactive
Author: Masamitsu MURASE
Author-email: masamitsu.murase@gmail.com
License: MIT
Project-URL: Bug Reports, https://github.com/masamitsu-murase/msal_interactive/issues
Project-URL: Source, https://github.com/masamitsu-murase/msal_interactive
Keywords: MSAL OAuth2
Platform: UNKNOWN
Requires-Python: !=3.0.*, !=3.1.*, !=3.2.*, !=3.3.*, !=3.4.*, <4
